bump.py
poutils-0.24.dist-info/licenses/LICENSE
poutils-0.24.dist-info/METADATA
poutils-0.24.dist-info/WHEEL
poutils-0.24.dist-info/top_level.txt
poutils-0.24.dist-info/RECORD
