Metadata-Version: 2.4
Name: poutils
Version: 0.24
Summary: Gettext related tools: spellcheck, line wrapping etc...
Author-email: Jules Lasne <jules.lasne@gmail.com>
License-Expression: MIT
Project-URL: Homepage, https://git.afpy.org/AFPy/poutils
Keywords: poutils,gettext,powrap,pospell,pogrep,potodo,pomerge,padpo,pofuzzy-helper
License-File: LICENSE
Requires-Dist: powrap>=1.0.2
Requires-Dist: pospell>=1.3
Requires-Dist: pogrep>=0.1.4
Requires-Dist: potodo>=0.35
Requires-Dist: pomerge>=0.2.1
Requires-Dist: padpo>=0.12.0
Requires-Dist: sphinx-lint>=1.0.2
Requires-Dist: pofuzzy-helper>=0.1.2
Dynamic: license-file
